mps_youtube/__init__.py
mps_youtube/c.py
mps_youtube/cache.py
mps_youtube/config.py
mps_youtube/content.py
mps_youtube/contentquery.py
mps_youtube/description_parser.py
mps_youtube/g.py
mps_youtube/helptext.py
mps_youtube/history.py
mps_youtube/init.py
mps_youtube/main.py
mps_youtube/mpris.py
mps_youtube/paths.py
mps_youtube/player.py
mps_youtube/playlist.py
mps_youtube/playlists.py
mps_youtube/screen.py
mps_youtube/streams.py
mps_youtube/terminalsize.py
mps_youtube/util.py
mps_youtube/commands/__init__.py
mps_youtube/commands/album_search.py
mps_youtube/commands/config.py
mps_youtube/commands/download.py
mps_youtube/commands/generate_playlist.py
mps_youtube/commands/lastfm.py
mps_youtube/commands/local_playlist.py
mps_youtube/commands/misc.py
mps_youtube/commands/play.py
mps_youtube/commands/search.py
mps_youtube/commands/songlist.py
mps_youtube/commands/spotify_playlist.py
mps_youtube/listview/__init__.py
mps_youtube/listview/base.py
mps_youtube/listview/livestream.py
mps_youtube/listview/songtitle.py
mps_youtube/listview/user.py
mps_youtube-0.2.8.data/data/share/applications/mps-youtube.desktop
mps_youtube-0.2.8.dist-info/DESCRIPTION.rst
mps_youtube-0.2.8.dist-info/METADATA
mps_youtube-0.2.8.dist-info/RECORD
mps_youtube-0.2.8.dist-info/WHEEL
mps_youtube-0.2.8.dist-info/entry_points.txt
mps_youtube-0.2.8.dist-info/metadata.json
mps_youtube-0.2.8.dist-info/top_level.txt
