Metadata-Version: 2.0
Name: mps-youtube
Version: 0.2.8
Summary: Terminal based YouTube player and downloader
Home-page: https://github.com/mps-youtube/mps-youtube
Author: np1
Author-email: np1nagev@gmail.com
License: UNKNOWN
Download-URL: https://github.com/mps-youtube/mps-youtube/archive/v0.2.8.tar.gz
Keywords: video,music,audio,youtube,stream,download
Platform: UNKNOWN
Classifier: Topic :: Utilities
Classifier: Topic :: Internet :: WWW/HTTP
Classifier: Topic :: Multimedia :: Sound/Audio :: Players
Classifier: Topic :: Multimedia :: Video
Classifier: Environment :: Console
Classifier: Environment :: Win32 (MS Windows)
Classifier: Environment :: MacOS X
Classifier: Operating System :: POSIX :: Linux
Classifier: Operating System :: MacOS
Classifier: Operating System :: MacOS :: MacOS 9
Classifier: Operating System :: MacOS :: MacOS X
Classifier: Operating System :: Microsoft
Classifier: Operating System :: Microsoft :: Windows :: Windows 7
Classifier: Operating System :: Microsoft :: Windows :: Windows XP
Classifier: Operating System :: Microsoft :: Windows :: Windows Vista
Classifier: Intended Audience :: End Users/Desktop
Classifier: Programming Language :: Python
Classifier: Programming Language :: Python :: 3
Classifier: Programming Language :: Python :: 3.3
Classifier: Programming Language :: Python :: 3.4
Classifier: Programming Language :: Python :: 3 :: Only
Classifier: Development Status :: 5 - Production/Stable
Classifier: License :: OSI Approved :: GNU General Public License v3 (GPLv3)
Requires-Dist: pafy (!=0.4.0,!=0.4.1,!=0.4.2,>=0.3.82)
